GlueTools/__init__.py
GlueTools/myfunctions.py
gluetools-0.0.8.dist-info/METADATA
gluetools-0.0.8.dist-info/WHEEL
gluetools-0.0.8.dist-info/top_level.txt
gluetools-0.0.8.dist-info/RECORD
