Metadata-Version: 2.4
Name: GlueTools
Version: 0.0.8
Summary: Librería con funciones utilizadas recurrentemente por el Equipo BI
Home-page: https://github.com/yddolem
Author: Meloddy Guzmán Palma
Author-email: guzmanpalmamel@gmail.com
License: MIT
Requires-Dist: setuptools
Dynamic: author
Dynamic: author-email
Dynamic: description
Dynamic: description-content-type
Dynamic: home-page
Dynamic: license
Dynamic: requires-dist
Dynamic: summary
